cert_human/__init__.py
cert_human/__version__.py
cert_human-1.0.7.data/scripts/cert_human_cli.py
cert_human-1.0.7.dist-info/LICENSE
cert_human-1.0.7.dist-info/METADATA
cert_human-1.0.7.dist-info/WHEEL
cert_human-1.0.7.dist-info/top_level.txt
cert_human-1.0.7.dist-info/RECORD
