Metadata-Version: 2.1
Name: cert-human
Version: 1.0.7
Summary: SSL Certificates for Humans.
Home-page: https://github.com/lifehackjim/cert_human
Author: Jim Olsen
Author-email: jim@lifehack.com
License: MIT
Platform: UNKNOWN
Classifier: Development Status :: 5 - Production/Stable
Classifier: Intended Audience :: Developers
Classifier: Natural Language :: English
Classifier: License :: OSI Approved :: MIT License
Classifier: Programming Language :: Python
Classifier: Programming Language :: Python :: 2
Classifier: Programming Language :: Python :: 2.7
Classifier: Programming Language :: Python :: 3
Classifier: Programming Language :: Python :: 3.7
Classifier: Programming Language :: Python :: Implementation :: CPython
Classifier: Programming Language :: Python :: Implementation :: PyPy
Requires-Python: >=2.7, !=3.0.*, !=3.1.*, !=3.2.*, !=3.3.*
Requires-Dist: requests[security]
Requires-Dist: pathlib2 ; python_version < "3.0"
